neuralviz/__init__.py
neuralviz/visualizer.py
neuralviz-0.6.1.dist-info/METADATA
neuralviz-0.6.1.dist-info/WHEEL
neuralviz-0.6.1.dist-info/top_level.txt
neuralviz-0.6.1.dist-info/RECORD
